mj_package/__init__.py
mj_package/core.py
mj_package/test/__init__.py
mj_package/test/test_add.py
mj_package/test/test_syb.py
mj_package-0.0.1.dist-info/METADATA
mj_package-0.0.1.dist-info/WHEEL
mj_package-0.0.1.dist-info/entry_points.txt
mj_package-0.0.1.dist-info/top_level.txt
mj_package-0.0.1.dist-info/RECORD
