Metadata-Version: 2.1
Name: mj-package
Version: 0.0.1
Summary: Personal ml packages
Home-page: http://gitXXXX
Author: Marc Juillard
Author-email: dont_ask@gmail.com
License: UNKNOWN
Platform: UNKNOWN
